unrealzap/__init__.py
unrealzap/audio_helper.py
unrealzap/bug_zapper.py
unrealzap/config.json
unrealzap/config.py
unrealzap/db_helper.py
unrealzap/kill_tracker.py
unrealzap/sounds/dominating.wav
unrealzap/sounds/double_kill.wav
unrealzap/sounds/first_blood.wav
unrealzap/sounds/godlike.wav
unrealzap/sounds/headshot.wav
unrealzap/sounds/killing_spree.wav
unrealzap/sounds/monster_kill.wav
unrealzap/sounds/multi_kill.wav
unrealzap/sounds/rampage.wav
unrealzap/sounds/ultra_kill.wav
unrealzap/sounds/unstoppable.wav
unrealzap/time_tracker.py
unrealzap-0.1.1.dist-info/METADATA
unrealzap-0.1.1.dist-info/WHEEL
unrealzap-0.1.1.dist-info/licenses/LICENSE
unrealzap-0.1.1.dist-info/RECORD
