Metadata-Version: 2.4
Name: unrealzap
Version: 0.1.1
Summary: Unreal Tournament bug zapper
License-Expression: MIT
License-File: LICENSE
Author: Danny Stewart
Author-email: danny@stewart.cc
Requires-Python: >=3.12,<4.0
Classifier: Programming Language :: Python :: 3
Classifier: Programming Language :: Python :: 3.12
Classifier: Programming Language :: Python :: 3.13
Classifier: Programming Language :: Python :: 3.14
Requires-Dist: numpy (>=2.4.2,<3.0.0)
Requires-Dist: polykit (>=0.14.6,<0.15.0)
Requires-Dist: pyalsaaudio (>=0.11.0,<0.12.0) ; sys_platform == "linux"
Requires-Dist: pygame (>=2.6.1,<3.0.0)
Requires-Dist: scipy (>=1.17.0,<2.0.0)
